{".class": "MypyFile", "_fullname": "hpcrocket.core.application", "future_import_flags": [], "is_partial_stub_package": false, "is_stub": false, "names": {".class": "SymbolTable", "Application": {".class": "SymbolTableNode", "kind": "Gdef", "node": {".class": "TypeInfo", "_promote": [], "abstract_attributes": [], "alt_promote": null, "bases": ["builtins.object"], "dataclass_transform_spec": null, "declared_metaclass": null, "defn": {".class": "ClassDef", "fullname": "hpcrocket.core.application.Application", "name": "Application", "type_vars": []}, "deletable_attributes": [], "flags": [], "fullname": "hpcrocket.core.application.Application", "has_param_spec_type": false, "metaclass_type": null, "metadata": {}, "module_name": "hpcrocket.core.application", "mro": ["hpcrocket.core.application.Application", "builtins.object"], "names": {".class": "SymbolTable", "__init__": {".class": "SymbolTableNode", "kind": "Mdef", "node": {".class": "FuncDef", "abstract_status": 0, "arg_kinds": [0, 0, 0, 0], "arg_names": ["self", "executor", "filesystem_factory", "ui"], "dataclass_transform_spec": null, "flags": [], "fullname": "hpcrocket.core.application.Application.__init__", "name": "__init__", "type": {".class": "CallableType", "arg_kinds": [0, 0, 0, 0], "arg_names": ["self", "executor", "filesystem_factory", "ui"], "arg_types": ["hpcrocket.core.application.Application", "hpcrocket.core.executor.CommandExecutor", "hpcrocket.core.filesystem._filesystem.FilesystemFactory", "hpcrocket.ui.UI"], "bound_args": [], "def_extras": {"first_arg": "self"}, "fallback": "builtins.function", "from_concatenate": false, "implicit": false, "is_ellipsis_args": false, "name": "__init__ of Application", "ret_type": {".class": "NoneType"}, "type_guard": null, "unpack_kwargs": false, "variables": []}}}, "_executor": {".class": "SymbolTableNode", "implicit": true, "kind": "Mdef", "node": {".class": "Var", "flags": ["is_inferred"], "fullname": "hpcrocket.core.application.Application._executor", "name": "_executor", "type": "hpcrocket.core.executor.CommandExecutor"}}, "_get_workflow": {".class": "SymbolTableNode", "kind": "Mdef", "node": {".class": "FuncDef", "abstract_status": 0, "arg_kinds": [0, 0, 0], "arg_names": ["self", "executor", "options"], "dataclass_transform_spec": null, "flags": [], "fullname": "hpcrocket.core.application.Application._get_workflow", "name": "_get_workflow", "type": {".class": "CallableType", "arg_kinds": [0, 0, 0], "arg_names": ["self", "executor", "options"], "arg_types": ["hpcrocket.core.application.Application", "hpcrocket.core.executor.CommandExecutor", {".class": "TypeAliasType", "args": [], "type_ref": "hpcrocket.core.launchoptions.Options"}], "bound_args": [], "def_extras": {"first_arg": "self"}, "fallback": "builtins.function", "from_concatenate": false, "implicit": false, "is_ellipsis_args": false, "name": "_get_workflow of Application", "ret_type": "hpcrocket.core.workflows.workflow.Workflow", "type_guard": null, "unpack_kwargs": false, "variables": []}}}, "_run_workflow": {".class": "SymbolTableNode", "kind": "Mdef", "node": {".class": "FuncDef", "abstract_status": 0, "arg_kinds": [0, 0], "arg_names": ["self", "options"], "dataclass_transform_spec": null, "flags": [], "fullname": "hpcrocket.core.application.Application._run_workflow", "name": "_run_workflow", "type": {".class": "CallableType", "arg_kinds": [0, 0], "arg_names": ["self", "options"], "arg_types": ["hpcrocket.core.application.Application", {".class": "TypeAliasType", "args": [], "type_ref": "hpcrocket.core.launchoptions.Options"}], "bound_args": [], "def_extras": {"first_arg": "self"}, "fallback": "builtins.function", "from_concatenate": false, "implicit": false, "is_ellipsis_args": false, "name": "_run_workflow of Application", "ret_type": "builtins.int", "type_guard": null, "unpack_kwargs": false, "variables": []}}}, "_ui": {".class": "SymbolTableNode", "implicit": true, "kind": "Mdef", "node": {".class": "Var", "flags": ["is_inferred"], "fullname": "hpcrocket.core.application.Application._ui", "name": "_ui", "type": "hpcrocket.ui.UI"}}, "_workflow": {".class": "SymbolTableNode", "implicit": true, "kind": "Mdef", "node": {".class": "Var", "flags": ["is_inferred"], "fullname": "hpcrocket.core.application.Application._workflow", "name": "_workflow", "type": "hpcrocket.core.workflows.workflow.Workflow"}}, "cancel": {".class": "SymbolTableNode", "kind": "Mdef", "node": {".class": "FuncDef", "abstract_status": 0, "arg_kinds": [0], "arg_names": ["self"], "dataclass_transform_spec": null, "flags": [], "fullname": "hpcrocket.core.application.Application.cancel", "name": "cancel", "type": {".class": "CallableType", "arg_kinds": [0], "arg_names": ["self"], "arg_types": ["hpcrocket.core.application.Application"], "bound_args": [], "def_extras": {"first_arg": "self"}, "fallback": "builtins.function", "from_concatenate": false, "implicit": false, "is_ellipsis_args": false, "name": "cancel of Application", "ret_type": "builtins.int", "type_guard": null, "unpack_kwargs": false, "variables": []}}}, "fs_factory": {".class": "SymbolTableNode", "implicit": true, "kind": "Mdef", "node": {".class": "Var", "flags": ["is_inferred"], "fullname": "hpcrocket.core.application.Application.fs_factory", "name": "fs_factory", "type": "hpcrocket.core.filesystem._filesystem.FilesystemFactory"}}, "run": {".class": "SymbolTableNode", "kind": "Mdef", "node": {".class": "FuncDef", "abstract_status": 0, "arg_kinds": [0, 0], "arg_names": ["self", "options"], "dataclass_transform_spec": null, "flags": [], "fullname": "hpcrocket.core.application.Application.run", "name": "run", "type": {".class": "CallableType", "arg_kinds": [0, 0], "arg_names": ["self", "options"], "arg_types": ["hpcrocket.core.application.Application", {".class": "TypeAliasType", "args": [], "type_ref": "hpcrocket.core.launchoptions.Options"}], "bound_args": [], "def_extras": {"first_arg": "self"}, "fallback": "builtins.function", "from_concatenate": false, "implicit": false, "is_ellipsis_args": false, "name": "run of Application", "ret_type": "builtins.int", "type_guard": null, "unpack_kwargs": false, "variables": []}}}}, "self_type": null, "slots": null, "tuple_type": null, "type_vars": [], "typeddict_type": null}}, "CommandExecutor": {".class": "SymbolTableNode", "cross_ref": "hpcrocket.core.executor.CommandExecutor", "kind": "Gdef"}, "FilesystemFactory": {".class": "SymbolTableNode", "cross_ref": "hpcrocket.core.filesystem._filesystem.FilesystemFactory", "kind": "Gdef"}, "Options": {".class": "SymbolTableNode", "cross_ref": "hpcrocket.core.launchoptions.Options", "kind": "Gdef"}, "SlurmController": {".class": "SymbolTableNode", "cross_ref": "hpcrocket.core.slurmcontroller.SlurmController", "kind": "Gdef"}, "UI": {".class": "SymbolTableNode", "cross_ref": "hpcrocket.ui.UI", "kind": "Gdef"}, "Workflow": {".class": "SymbolTableNode", "cross_ref": "hpcrocket.core.workflows.workflow.Workflow", "kind": "Gdef"}, "__annotations__": {".class": "SymbolTableNode", "kind": "Gdef", "node": {".class": "Var", "flags": ["is_ready"], "fullname": "hpcrocket.core.application.__annotations__", "name": "__annotations__", "type": {".class": "Instance", "args": ["builtins.str", {".class": "AnyType", "missing_import_name": null, "source_any": null, "type_of_any": 6}], "type_ref": "builtins.dict"}}}, "__doc__": {".class": "SymbolTableNode", "kind": "Gdef", "node": {".class": "Var", "flags": ["is_ready"], "fullname": "hpcrocket.core.application.__doc__", "name": "__doc__", "type": "builtins.str"}}, "__file__": {".class": "SymbolTableNode", "kind": "Gdef", "node": {".class": "Var", "flags": ["is_ready"], "fullname": "hpcrocket.core.application.__file__", "name": "__file__", "type": "builtins.str"}}, "__name__": {".class": "SymbolTableNode", "kind": "Gdef", "node": {".class": "Var", "flags": ["is_ready"], "fullname": "hpcrocket.core.application.__name__", "name": "__name__", "type": "builtins.str"}}, "__package__": {".class": "SymbolTableNode", "kind": "Gdef", "node": {".class": "Var", "flags": ["is_ready"], "fullname": "hpcrocket.core.application.__package__", "name": "__package__", "type": "builtins.str"}}, "get_error_message": {".class": "SymbolTableNode", "cross_ref": "hpcrocket.core.errors.get_error_message", "kind": "Gdef"}, "make_workflow": {".class": "SymbolTableNode", "cross_ref": "hpcrocket.core.workflowfactory.make_workflow", "kind": "Gdef"}}, "path": "/Users/marcus/Documents/Projects/hpc-rocket/hpcrocket/core/application.py"}