{"data_mtime":1685978554,"dep_lines":[3,6,8,9,12,1,2,4,5,254,1,1,1,1,1,1,1,1,1,1,1,1,1,1,1,1,1,1,1,1,1,20],"dep_prios":[5,5,5,5,25,10,5,5,5,20,5,20,20,20,20,20,20,20,20,20,20,20,30,30,30,30,30,30,30,30,30,5],"dependencies":["os.path","urllib.request","rdflib.store","rdflib.term","rdflib.graph","logging","os","threading","typing","time","builtins","traceback","re","copy","string","itertools","types","collections","html","sys","warnings","pprint","_typeshed","abc","array","ctypes","genericpath","mmap","pickle","posixpath","typing_extensions"],"hash":"1a630d893e4627c66e66be074d326b7e455a5ed8f8392eaf24e0c7ae03c8eddb","id":"rdflib.plugins.stores.berkeleydb","ignore_all":true,"interface_hash":"75f4d8172b3b1e64be41aa85d61a4fcfa69a33f519d7ce39d44a1154c0a0ccc1","mtime":1684999181,"options":{"allow_redefinition":false,"allow_untyped_globals":false,"always_false":[],"always_true":[],"bazel":false,"check_untyped_defs":false,"disable_bytearray_promotion":false,"disable_error_code":[],"disable_memoryview_promotion":false,"disabled_error_codes":[],"disallow_any_decorated":false,"disallow_any_explicit":false,"disallow_any_expr":false,"disallow_any_generics":false,"disallow_any_unimported":false,"disallow_incomplete_defs":false,"disallow_subclassing_any":false,"disallow_untyped_calls":false,"disallow_untyped_decorators":false,"disallow_untyped_defs":false,"enable_error_code":[],"enabled_error_codes":[],"follow_imports":"silent","follow_imports_for_stubs":false,"ignore_errors":false,"ignore_missing_imports":false,"implicit_optional":false,"implicit_reexport":true,"local_partial_types":false,"mypyc":false,"platform":"linux","plugins":[],"strict_concatenate":false,"strict_equality":false,"strict_optional":true,"warn_no_return":true,"warn_return_any":false,"warn_unreachable":false,"warn_unused_ignores":false},"path":"/home/upgrd/.local/lib/python3.11/site-packages/rdflib/plugins/stores/berkeleydb.py","plugin_data":null,"size":29955,"suppressed":["berkeleydb"],"version_id":"1.3.0"}